dbt/__init__.py
dbt/adapters/__init__.py
dbt/adapters/azuresynapse/__init__.py
dbt/adapters/azuresynapse/connections.py
dbt/adapters/azuresynapse/impl.py
dbt/include/__init__.py
dbt/include/azuresynapse/__init__.py
dbt/include/azuresynapse/dbt_project.yml
dbt/include/azuresynapse/macros/adapters.sql
dbt/include/azuresynapse/macros/catalog.sql
dbt/include/azuresynapse/macros/materializations/snapshot/snapshot_merge.sql
dbt/include/azuresynapse/macros/materializations/snapshot/strategy.sql
dbt_azuresynapse-1.0.3.dist-info/LICENSE.md
dbt_azuresynapse-1.0.3.dist-info/METADATA
dbt_azuresynapse-1.0.3.dist-info/WHEEL
dbt_azuresynapse-1.0.3.dist-info/top_level.txt
dbt_azuresynapse-1.0.3.dist-info/RECORD
