Metadata-Version: 2.1
Name: dbt-azuresynapse
Version: 1.0.3
Summary: The azuresynapse adapter plugin for dbt (data build tool)
Home-page: https://github.com/embold-health/dbt-azuresynapse
Author: Embold Health
Author-email: techteam@emboldhealth.com
License: UNKNOWN
Platform: UNKNOWN
Requires-Python: >3.6.3
Requires-Dist: dbt-core (>=0.17.2)
Requires-Dist: pyodbc (==4.0.30)
